textipic/__init__.py
textipic/textipic.py
textipic-0.1.dist-info/METADATA
textipic-0.1.dist-info/WHEEL
textipic-0.1.dist-info/entry_points.txt
textipic-0.1.dist-info/top_level.txt
textipic-0.1.dist-info/RECORD
