Metadata-Version: 2.1
Name: textipic
Version: 0.1
Summary: A script to generate images from text
Home-page: https://x.com/Lanaev0li
Author: Avinion
Author-email: shizofrin@gmail.com
License: MIT
Requires-Dist: Pillow
